README.rst
setup.py
metaframe/__init__.py
metaframe/metaframe.py
metaframe.egg-info/PKG-INFO
metaframe.egg-info/SOURCES.txt
metaframe.egg-info/dependency_links.txt
metaframe.egg-info/top_level.txt